truestrive/__init__.py
truestrive/libs/__init__.py
truestrive/libs/filetypes/__init__.py
truestrive/libs/filetypes/common.py
truestrive/libs/filetypes/file.py
truestrive/libs/filetypes/file_signature.json
truestrive/libs/filetypes/utils.py
validate_extension_file-0.0.3.dist-info/LICENSE
validate_extension_file-0.0.3.dist-info/METADATA
validate_extension_file-0.0.3.dist-info/WHEEL
validate_extension_file-0.0.3.dist-info/top_level.txt
validate_extension_file-0.0.3.dist-info/RECORD
