Metadata-Version: 2.1
Name: validate-extension-file
Version: 0.0.3
Summary: Libs check filetype
Author: TrueStrive
Author-email: 
Classifier: Programming Language :: Python
Classifier: Programming Language :: Python :: 3.8
Classifier: Programming Language :: Python :: 3.9
License-File: LICENSE
